LICENSE
MANIFEST.in
Makefile
README.rst
setup.py
pyhistorian.egg-info/PKG-INFO
pyhistorian.egg-info/SOURCES.txt
pyhistorian.egg-info/dependency_links.txt
pyhistorian.egg-info/not-zip-safe
pyhistorian.egg-info/requires.txt
pyhistorian.egg-info/top_level.txt
specs/__init__.py
specs/almost_plain_text_history.py
specs/bug_regex.py
specs/colors.py
specs/error_colors.py
specs/executing_snippet_after_steps.py
specs/executing_snippet_before_steps.py
specs/failures_colors.py
specs/feature_injection.py
specs/finding_scenarios_in_module.py
specs/inheriting_from_cenario_ptbr.py
specs/output_units.py
specs/pending.py
specs/pending_colors.py
specs/run_specs.py
specs/scenario.py
specs/step.py
specs/story.py
specs/story_pt_br.py
specs/story_template_with_colors.py
specs/stringio_feature.py
specs/traceback_message.py
specs/unittest_integration.py
src/__init__.py
src/language.py
src/output.py
src/scenario.py
src/steps.py
src/story.py
src/suite.py