Metadata-Version: 1.0
Name: pyhistorian
Version: 0.6.8
Summary: pyhistorian is a BDD tool for writing specifications using Given-When-Then template
Home-page: http://github.com/hugobr/pyhistorian
Author: Hugo Lopes Tavares
Author-email: hltbra@gmail.com
License: MIT License
Keywords: bdd dsl python
Platform: UNKNOWN
Classifier: Development Status :: 4 - Beta
Classifier: Environment :: Console
Classifier: Intended Audience :: Developers
Classifier: License :: OSI Approved :: MIT License
Classifier: Programming Language :: Python
Classifier: Topic :: Software Development :: Documentation
Classifier: Topic :: Software Development :: Testing
